{
  "empty": {
    "image": "/img/uploads/search-bg.png",
    "title": "Nichts gefunden",
    "description": "Versuchen Sie, nach etwas anderem zu suchen"
  },
  "providersLabel": "Provider",
  "sortLabel": "Sortieren nach",
  "seo": {
    "text": {
      "visible": ""
    },
    "title": "Win.Casino | Finden Sie Lieblings-Slots und -Spiele"
  },
  "sortOptions": [
    {
      "label": "Most popular",
      "sortBy": "default",
      "sortOrder": "asc"
    },
    {
      "label": "A-Z",
      "sortBy": "name",
      "sortOrder": "asc"
    },
    {
      "label": "Z-A",
      "sortBy": "name",
      "sortOrder": "desc"
    }
  ],
  "allProvidersOption": "All providers",
  "clearProviders": "Alles löschen"
}
