{
  "socials": {
    "isShow": false
  },
  "bottomMenu": [
    {
      "label": "Støtte",
      "url": "/contact",
      "icon": "live-support"
    }
  ],
  "userMenu": [
    {
      "icon": "heart",
      "label": "Favoritt",
      "url": "/favorites"
    },
    {
      "url": "/recently-played",
      "icon": "history",
      "label": "Nylig spilt"
    }
  ],
  "bonusesMenu": [
    {
      "items": [
        {
          "label": "Velkomstpakke",
          "url": "/welcome-package"
        },
        {
          "url": "/bonus/monday-reload-bonus",
          "label": "Mandag Reload Bonus"
        },
        {
          "url": "/bonus/wednesday-free-spins",
          "label": "Onsdag Gratisspinn"
        },
        {
          "url": "/bonus/weekly-cashback",
          "label": "Ukentlig Cashback"
        }
      ],
      "label": "Bonus",
      "icon": "bonuses"
    }
  ],
  "ctaMenu": {
    "isShow": false
  },
  "topMenu": {
    "integratedElement": {
      "label": "AVIATOR",
      "url": "https://win.city/games/spribe-aviator?real=true",
      "isShow": true,
      "backgroundImage": "/img/uploads/cta-bg.png",
      "order": 2
    },
    "items": [
      {
        "url": "/games?category=slots",
        "label": "Spilleautomat",
        "icon": "slots"
      },
      {
        "url": "/games?category=live",
        "icon": "live-casino",
        "label": "Live Casino"
      },
      {
        "label": "bordspill",
        "url": "/games?category=table",
        "icon": "table-games"
      },
      {
        "gameList": [
          {
            "gameIdentity": "crash-x-turbo-games"
          },
          {
            "gameIdentity": "dice-twice-turbo-games"
          },
          {
            "gameIdentity": "mines-turbo-games"
          },
          {
            "gameIdentity": "turbo-games-turboplinko"
          }
        ],
        "label": "Turbo spill",
        "url": "/games?category=turbogames",
        "icon": "turbo-games"
      },
      {
        "label": "Oddsspill",
        "url": "/betting",
        "icon": "sport-book"
      }
    ]
  },
  "sidebarFooterMenu": [
    {
      "label": "T&C",
      "url": "/static/terms-and-conditions"
    },
    {
      "url": "/static/bonus-terms",
      "label": "Bonusbetingelser"
    },
    {
      "url": "/questions",
      "label": "F.A.Q"
    },
    {
      "url": "/static/privacy-policy",
      "label": "personvern"
    },
    {
      "url": "/static/gambling-with-responsibility",
      "label": "Spill ansvarlig"
    },
    {
      "url": "/static/kyc-policy",
      "label": "KYC-Politikk"
    }
  ],
  "tokenMenu": [
    {
      "label": "Win.Casino Coin",
      "url": "/sbt-token",
      "icon": "tfs-token"
    }
  ],
  "gamesToggler": {
    "buttonFirst": {
      "label": "Casino",
      "url": "/main",
      "icon": "cherry"
    },
    "buttonSecond": {
      "label": "Sport",
      "url": "/betting",
      "icon": "sport"
    }
  },
  "chatLabel": "chat"
}
