{
  "pageUrl": "weekly-cashback",
  "termsLabel": "Condiciones de la bonificación:",
  "termsContent": "**1.** Cada semana calculamos la diferencia total entre las apuestas realizadas y los pagos de esas apuestas y pagamos el reembolso.",
  "button": {
    "label": "Conseguir bonificación"
  },
  "backgroundColor": "gray",
  "subtitle": "Recibe tu cashback hasta un 15% todos los martes",
  "title": "Reembolso semanal",
  "image": "https://win.city/img/uploads/weekly-big.webp",
  "description": "Todos los martes podrás recuperar una parte de tu dinero apostado gracias a nuestro reembolso semanal. Recibe el tuyo",
  "seo": {
    "title": "Win.Casino | Cashback Semanal"
  }
}
