{
  "bonusCodeIncorrect": {
    "title": "Siamo spiacenti, ma il codice bonus inserito non è corretto."
  },
  "bonusCodeNotAvailable": {
    "title": "Siamo spiacenti, ma il bonus con il codice bonus inserito non è disponibile per voi."
  },
  "bonusIssued": {
    "title": "Rilasciato",
    "description": "Il bonus {amount} è stato emesso"
  },
  "bonusActivated": {
    "title": "Attivo",
    "description": "Il bonus {amount} è stato attivato"
  },
  "bonusPlayed": {
    "title": "Terminato",
    "description": "Il bonus {amount} è stato scommesso con successo. Le vincite sono già presenti nel saldo reale."
  },
  "bonusCanceled": {
    "title": "Annullato",
    "description": "Il bonus {amount} è stato annullato"
  },
  "bonusExpired": {
    "title": "Scaduto",
    "description": "Il bonus {amount} è scaduto"
  },
  "bonusLost": {
    "title": "Perso",
    "description": "Il bonus {amount} non è stato scommesso"
  }
}